loki_django_logger/__init__.py
loki_django_logger/handler.py
loki_django_logger-1.0.9.dist-info/licenses/LICENSE
tests/__init__.py
tests/test_handler.py
loki_django_logger-1.0.9.dist-info/METADATA
loki_django_logger-1.0.9.dist-info/WHEEL
loki_django_logger-1.0.9.dist-info/top_level.txt
loki_django_logger-1.0.9.dist-info/RECORD
