Metadata-Version: 2.4
Name: loki-django-logger
Version: 1.0.9
Summary: Loki logger for Django applications
Home-page: https://github.com/irwinrex/django-loki-logger
Author: Irwin Rex
Author-email: irwinrex.a@gmail.com
Keywords: django loki logger async log-aggregation
Classifier: Development Status :: 5 - Production/Stable
Classifier: Framework :: Django
Classifier: Intended Audience :: Developers
Classifier: License :: OSI Approved :: MIT License
Classifier: Programming Language :: Python :: 3.8
Classifier: Programming Language :: Python :: 3.9
Classifier: Programming Language :: Python :: 3.10
Classifier: Programming Language :: Python :: 3.11
Classifier: Programming Language :: Python :: 3.12
Classifier: Topic :: System :: Logging
Requires-Python: >=3.8
License-File: LICENSE
Requires-Dist: Django>=4.0
Requires-Dist: requests>=2.26.0
Dynamic: author
Dynamic: author-email
Dynamic: classifier
Dynamic: description
Dynamic: description-content-type
Dynamic: home-page
Dynamic: keywords
Dynamic: license-file
Dynamic: requires-dist
Dynamic: requires-python
Dynamic: summary
